
[
  {
    "id": 1,
    "name": "Механическая клавиатура RGB",
    "price": 89.99,
    "isIn": true,
    "releaseDate": "2023-05-15",
    "type": "keyboard",
    "imageUrl": "assets/images/key1.png"
  },
  {
    "id": 2,
    "name": "Беспроводная мышка MX Master",
    "price": 59.99,
    "isIn": true,
    "releaseDate": "2023-02-10",
    "type": "mouse",
    "imageUrl": "assets/images/[MConverter.eu] 8fa0e8ce-3a24-4194-bc93-8598b7cbd389 (1).png"
  },
  {
    "id": 3,
    "name": "Игровые наушники Pro X",
    "price": 129.99,
    "isIn": false,
    "releaseDate": "2023-07-22",
    "type": "headphones",
    "imageUrl": "assets/images/4 2.png"
  }
]